easydebugger/__init__.py
easydebugger-1.3.0.dist-info/LICENSE
easydebugger-1.3.0.dist-info/METADATA
easydebugger-1.3.0.dist-info/WHEEL
easydebugger-1.3.0.dist-info/top_level.txt
easydebugger-1.3.0.dist-info/RECORD
