Metadata-Version: 2.1
Name: easydebugger
Version: 1.3.0
Summary: A clean Python debugging tool
Author: blob2763
Keywords: python,debugger
License-File: LICENSE
